enable/__init__.py
enable/_version.py
enable/abstract_overlay.py
enable/abstract_window.py
enable/api.py
enable/base.py
enable/base_tool.py
enable/brush.py
enable/canvas.py
enable/colors.py
enable/compass.py
enable/compiled_path.py
enable/component.py
enable/component_editor.py
enable/constraints_container.py
enable/container.py
enable/coordinate_box.py
enable/enable_traits.py
enable/events.py
enable/example_application.py
enable/example_canvas.py
enable/example_support.py
enable/font_metrics_provider.py
enable/graphics_context.py
enable/images.zip
enable/interactor.py
enable/kiva_graphics_context.py
enable/label.py
enable/markers.py
enable/native_scrollbar.py
enable/overlay_container.py
enable/scrolled.py
enable/simple_layout.py
enable/slider.py
enable/stacked_container.py
enable/stacked_layout.py
enable/testing.py
enable/text_field.py
enable/text_field_grid.py
enable/text_field_style.py
enable/text_grid.py
enable/toolkit.py
enable/toolkit_constants.py
enable/viewable.py
enable/viewport.py
enable/window.py
enable/drawing/__init__.py
enable/drawing/api.py
enable/drawing/drag_box.py
enable/drawing/drag_line.py
enable/drawing/drag_polygon.py
enable/drawing/drag_segment.py
enable/drawing/drawing_canvas.py
enable/drawing/drawing_tool.py
enable/drawing/point_line.py
enable/drawing/point_polygon.py
enable/examples/__init__.py
enable/examples/_etsdemo_info.py
enable/examples/_example_application.py
enable/examples/_example_canvas.py
enable/examples/_example_support.py
enable/examples/demo/enable/basic_draw.py
enable/examples/demo/enable/basic_move.py
enable/examples/demo/enable/brush_draw.py
enable/examples/demo/enable/canvas_demo.py
enable/examples/demo/enable/compass_example.py
enable/examples/demo/enable/component_demo.py
enable/examples/demo/enable/constraints_demo.enaml
enable/examples/demo/enable/constraints_demo.py
enable/examples/demo/enable/container_demo.py
enable-6.1.0.dist-info/METADATA
enable-6.1.0.dist-info/WHEEL
enable-6.1.0.dist-info/entry_points.txt
enable-6.1.0.dist-info/top_level.txt
enable-6.1.0.dist-info/RECORD
enable-6.1.0.dist-info/licenses/LICENSE.txt
