Metadata-Version: 2.4
Name: enable
Version: 6.1.0
Summary: low-level drawing and interaction
Home-page: https://github.com/enthought/enable/
Download-URL: https://github.com/enthought/enable/archive/6.1.0.tar.gz
Author: Enthought, Inc
Author-email: info@enthought.com
Maintainer: ETS Developers
Maintainer-email: enthought-dev@enthought.com
License: BSD
Platform: Windows
Platform: Linux
Platform: macOS
Platform: Unix
Platform: Solaris
Classifier: Development Status :: 5 - Production/Stable
Classifier: Intended Audience :: Developers
Classifier: Intended Audience :: Science/Research
Classifier: License :: OSI Approved :: BSD License
Classifier: Operating System :: MacOS
Classifier: Operating System :: Microsoft :: Windows
Classifier: Operating System :: OS Independent
Classifier: Operating System :: POSIX
Classifier: Operating System :: Unix
Classifier: Programming Language :: C
Classifier: Programming Language :: Python
Classifier: Topic :: Scientific/Engineering
Classifier: Topic :: Software Development
Classifier: Topic :: Software Development :: Libraries
Requires-Python: >=3.9
License-File: LICENSE.txt
Requires-Dist: numpy
Requires-Dist: pillow
Requires-Dist: traits>=6.2.0
Requires-Dist: traitsui
Requires-Dist: pyface>=7.2.0
Requires-Dist: fonttools
Provides-Extra: docs
Requires-Dist: enthought-sphinx-theme; extra == "docs"
Requires-Dist: sphinx; extra == "docs"
Requires-Dist: sphinx-copybutton; extra == "docs"
Provides-Extra: examples
Requires-Dist: chaco; extra == "examples"
Requires-Dist: mayavi; extra == "examples"
Requires-Dist: scipy; extra == "examples"
Requires-Dist: kiwisolver; extra == "examples"
Provides-Extra: layout
Requires-Dist: kiwisolver; extra == "layout"
Provides-Extra: pdf
Requires-Dist: reportlab; extra == "pdf"
Provides-Extra: svg
Requires-Dist: pyparsing; extra == "svg"
Provides-Extra: celiagg
Requires-Dist: celiagg; extra == "celiagg"
Provides-Extra: cairo
Requires-Dist: pycairo; extra == "cairo"
Provides-Extra: test
Requires-Dist: pyparsing; extra == "test"
Requires-Dist: PyPDF2<3.0; extra == "test"
Requires-Dist: setuptools; extra == "test"
Provides-Extra: pyside6
Requires-Dist: pyface[pyside6]; extra == "pyside6"
Requires-Dist: traitsui[pyside6]; extra == "pyside6"
Provides-Extra: pyside2
Requires-Dist: pyface[pyside2]; extra == "pyside2"
Requires-Dist: traitsui[pyside2]; extra == "pyside2"
Requires-Dist: pillow<10; extra == "pyside2"
Provides-Extra: pyqt6
Requires-Dist: pyface[pyqt6]; extra == "pyqt6"
Requires-Dist: traitsui[pyqt6]; extra == "pyqt6"
Provides-Extra: pyqt5
Requires-Dist: pyface[pyqt5]; extra == "pyqt5"
Requires-Dist: traitsui[pyqt5]; extra == "pyqt5"
Requires-Dist: pillow<10; extra == "pyqt5"
Provides-Extra: wx
Requires-Dist: pyface[wx]; extra == "wx"
Requires-Dist: traitsui[wx]; extra == "wx"
Provides-Extra: null
Dynamic: author
Dynamic: author-email
Dynamic: classifier
Dynamic: description
Dynamic: description-content-type
Dynamic: download-url
Dynamic: home-page
Dynamic: license
Dynamic: license-file
Dynamic: maintainer
Dynamic: maintainer-email
Dynamic: platform
Dynamic: provides-extra
Dynamic: requires-dist
Dynamic: requires-python
Dynamic: summary
